chronometre/__init__.py
chronometre/_chronometre.cpp
chronometre/_chronometre.cpython-314t-x86_64-linux-musl.so
chronometre.libs/libgcc_s-0cd532bd.so.1
chronometre.libs/libstdc++-5d72f927.so.6.0.33
chronometre-0.0.2.dist-info/METADATA
chronometre-0.0.2.dist-info/WHEEL
chronometre-0.0.2.dist-info/top_level.txt
chronometre-0.0.2.dist-info/RECORD
chronometre-0.0.2.dist-info/sboms/auditwheel.cdx.json
