Metadata-Version: 2.4
Name: chronometre
Version: 0.0.2
Summary: As 'chronomètre' is a 'stopwatch' this package offers a simple stopwatch
Requires-Python: >=3.11
Provides-Extra: test
Requires-Dist: pytest>=7.0; extra == "test"
